google_cloud_helper/BigQueryHelper.py
google_cloud_helper/GoogleBucketHelper.py
google_cloud_helper/SecretManagerHelper.py
google_cloud_helper/__init__.py
tests/test_BigQueryHelper.py
tests/test_GoogleBucketHelper.py
tests/test_SecretManagerHelper.py
google_cloud_helper-0.1.8.dist-info/METADATA
google_cloud_helper-0.1.8.dist-info/WHEEL
google_cloud_helper-0.1.8.dist-info/top_level.txt
google_cloud_helper-0.1.8.dist-info/RECORD
