Metadata-Version: 2.4
Name: google-cloud-helper
Version: 0.1.8
Summary: Add your description here
Project-URL: Homepage, https://github.com/SWRdata/google-cloud-helper.git
Requires-Python: >=3.11
Requires-Dist: google-cloud-bigquery>=3.35.0
Requires-Dist: google-cloud-secret-manager>=2.24.0
Requires-Dist: google-cloud-storage>=3.2.0
Requires-Dist: pandas>=2.3.1
Requires-Dist: pandas-gbq>=0.29.2
Requires-Dist: pre-commit>=4.2.0
Requires-Dist: pytest>=8.4.1
